decoreml/cli.py
decoreml-0.4.0.dist-info/METADATA
decoreml-0.4.0.dist-info/WHEEL
decoreml-0.4.0.dist-info/entry_points.txt
decoreml-0.4.0.dist-info/RECORD
