Metadata-Version: 2.1
Name: deCoreML
Version: 0.4.0
Summary: Find out why your CoreML model isn't running on the ANE!
Author: FL33TW00D
Author-email: chris@fleetwood.dev
Requires-Python: >=3.7,<4.0
Classifier: Programming Language :: Python :: 3
Classifier: Programming Language :: Python :: 3.7
Classifier: Programming Language :: Python :: 3.8
Classifier: Programming Language :: Python :: 3.9
Classifier: Programming Language :: Python :: 3.10
Classifier: Programming Language :: Python :: 3.11
Classifier: Programming Language :: Python :: 3.12
Requires-Dist: rich (>=13.4,<14.0)
